wrapperpkg/__init__.py
wrapperpkg-0.0.3.dist-info/Licence.txt
wrapperpkg-0.0.3.dist-info/METADATA
wrapperpkg-0.0.3.dist-info/WHEEL
wrapperpkg-0.0.3.dist-info/top_level.txt
wrapperpkg-0.0.3.dist-info/RECORD
