Metadata-Version: 2.1
Name: wrapperpkg
Version: 0.0.3
Summary: Streaming video data via networks
Author: NeuralNine (Florian Dedov)
Author-email: <mail@neuralnine.com>
Classifier: Development Status :: 1 - Planning
Classifier: Intended Audience :: Developers
Classifier: Programming Language :: Python :: 3
Classifier: Operating System :: Unix
Classifier: Operating System :: MacOS :: MacOS X
Classifier: Operating System :: Microsoft :: Windows
License-File: Licence.txt
